Workbook

Sheet 薪资结构
A1: 序号 | B1: 薪资项目 | C1: 项目类型 | D1: 金额(元) | E1: 薪酬带宽 Min | F1: 薪酬带宽 Mid | G1: 薪酬带宽 Max | H1: 比例 | I1: 计算基数 | J1: 计算方式 | K1: 发放周期 | L1: 备注
A2: 1 | B2: 基本工资 | C2: 固定薪资 | D2: 4500 | E2: 3500 | F2: 4500 | G2: 6000 | H2: - | I2: 合同约定 | J2: 按月固定发放 | K2: 月度 | L2: 当地最低工资以上
A3: 2 | B3: 岗位工资 | C3: 固定薪资 | D3: 1800 | E3: 1200 | F3: 1800 | G3: 2500 | H3: - | I3: 岗位职级 | J3: 按月固定发放 | K3: 月度 | L3: 根据岗位价值评估
A4: 3 | B4: 绩效工资 | C4: 浮动薪资 | D4: 2000 | E4: 1200 | F4: 2000 | G4: 3000 | H4: - | I4: 绩效考核得分 | J4: 绩效得分/100*标准 | K4: 月度 | L4: 与KPI挂钩
A5: 4 | B5: 加班工资 | C5: 浮动薪资 | D5: 650 | E5: - | F5: - | G5: - | H5: - | I5: 实际加班时长 | J5: 按劳动法1.5/2/3倍 | K5: 月度 | L5: 以基本工资为基数
A6: 5 | B6: 全勤奖 | C6: 津贴补贴 | D6: 260 | E6: - | F6: - | G6: - | H6: - | I6: 当月无缺勤 | J6: 满足条件全额发放 | K6: 月度 | L6: 迟到早退超3次取消
A7: 6 | B7: 餐补 | C7: 津贴补贴 | D7: 376.55 | E7: - | F7: - | G7: - | H7: - | I7: 出勤天数 | J7: 390/21.75*21 | K7: 月度 | L7: 按实际出勤计算
A8: 7 | B8: 交通补贴 | C8: 津贴补贴 | D8: 260 | E8: - | F8: - | G8: - | H8: - | I8: 固定 | J8: 按月固定发放 | K8: 月度 | L8: 外勤较多可上浮
A9: 8 | B9: 通讯补贴 | C9: 津贴补贴 | D9: 130 | E9: - | F9: - | G9: - | H9: - | I9: 固定 | J9: 按月固定发放 | K9: 月度 | L9: 运营岗位标配
A10: 9 | B10: 五险一金(个人) | C10: 代扣项 | D10: ='计算示例'!B20 | E10: - | F10: - | G10: - | H10: - | I10: 缴费基数*比例 | J10: 养老8%+医疗2%+失业0.5%+公积金 | K10: 月度 | L10: 单位另承担约30%
A11: 10 | B11: 个人所得税 | C11: 代扣项 | D11: ='计算示例'!B23 | E11: - | F11: - | G11: - | H11: - | I11: 应纳税所得额 | J11: 累计预扣法 | K11: 月度 | L11: 按个税法计算
A12: 11 | B12: 应发工资 | C12: 汇总 | D12: ='计算示例'!B19 | E12: - | F12: - | G12: - | H12: - | I12: 固定+浮动+补贴 | J12: SUM(固定+浮动+补贴) | K12: 月度 | L12: 税前总薪资
A13: 12 | B13: 实发工资 | C13: 汇总 | D13: ='计算示例'!B24 | E13: - | F13: - | G13: - | H13: - | I13: 应发-代扣项 | J13: 应发-五险一金-个税 | K13: 月度 | L13: 到手金额

Sheet 绩效考核
A1: 序号 | B1: 考核维度 | C1: 权重 | D1: 指标定义 | E1: 目标值 | F1: 评分标准 | G1: 数据来源 | H1: 考核周期 | I1: 备注
A2: 1 | B2: 销售额达成率 | C2: 25% | D2: 销售额达成实际/目标 | E2: >=90分 | F2: 达标100分；每低1分扣2-5分 | G2: 业务系统/主管评分 | H2: 月度 | I2: 核心指标
A3: 2 | B3: 订单处理效率 | C3: 15% | D3: 订单处理效实际/目标 | E3: >=85分 | F3: 达标100分；每低1分扣2-5分 | G3: 业务系统/主管评分 | H3: 月度 | I3: 辅助指标
A4: 3 | B4: 客户满意度 | C4: 15% | D4: 客户满意度 | E4: >=85分 | F4: 达标100分；每低1分扣2-5分 | G4: 业务系统/主管评分 | H4: 月度 | I4: 辅助指标
A5: 4 | B5: 库存准确率 | C5: 10% | D5: 库存准确实际/目标 | E5: >=85分 | F5: 达标100分；每低1分扣2-5分 | G5: 业务系统/主管评分 | H5: 月度 | I5: 辅助指标
A6: 5 | B6: 活动执行完成率 | C6: 10% | D6: 活动执行完成实际/目标 | E6: >=85分 | F6: 达标100分；每低1分扣2-5分 | G6: 业务系统/主管评分 | H6: 月度 | I6: 辅助指标
A7: 6 | B7: 数据报表准确率 | C7: 10% | D7: 数据报表准确实际/目标 | E7: >=85分 | F7: 达标100分；每低1分扣2-5分 | G7: 业务系统/主管评分 | H7: 月度 | I7: 辅助指标
A8: 7 | B8: 工作态度与协作 | C8: 10% | D8: 工作态度与协作 | E8: >=85分 | F8: 达标100分；每低1分扣2-5分 | G8: 业务系统/主管评分 | H8: 月度 | I8: 辅助指标
A9: 8 | B9: 学习成长 | C9: 5% | D9: 学习成长 | E9: >=85分 | F9: 达标100分；每低1分扣2-5分 | G9: 业务系统/主管评分 | H9: 月度 | I9: 辅助指标

Sheet 调薪机制
A1: 序号 | B1: 调薪类型 | C1: 适用条件 | D1: 调薪幅度 | E1: 生效时间 | F1: 审批流程 | G1: 备注
A2: 1 | B2: 试用期转正调薪 | C2: 试用期考核通过 | D2: 0-10% | E2: 转正次月 | F2: 部门主管→HR→总经理 | G2: 根据试用期表现定档
A3: 2 | B3: 年度普调 | C3: 入职满1年且年度绩效≥B | D3: 3-8% | E3: 次年1月 | F3: HR提案→管理层审批 | G3: 参考市场薪酬涨幅
A4: 3 | B4: 晋升调薪 | C4: 职级晋升 | D4: 10-25% | E4: 晋升次月 | F4: 部门提名→晋升评审→总经理 | G4: 每晋升1级至少10%
A5: 4 | B5: 绩效调薪 | C5: 连续2个季度绩效A或年度绩效A | D5: 5-15% | E5: 绩效评定次月 | F5: 主管申请→HR审核→总经理 | G5: 不与晋升调薪重复享受
A6: 5 | B6: 市场薪酬调整 | C6: 岗位市场薪酬显著变化 | D6: 5-10% | E6: 调整方案确认次月 | F6: HR调研→管理层审批 | G6: 需有薪酬调研数据支撑
A7: 6 | B7: 特殊贡献调薪 | C7: 重大项目突破/特殊贡献 | D7: 10-30% | E7: 贡献确认次月 | F7: 部门申请→总经理特批 | G7: 一事一议
A8: 7 | B8: 留任调薪 | C8: 核心人才面临外部高薪挖角 | D8: 10-20% | E8: 审批通过后次月 | F8: HR评估→总经理审批 | G8: 需签订服务期协议

Sheet 奖金方案
A1: 序号 | B1: 奖金类型 | C1: 适用岗位 | D1: 计算基数 | E1: 计提比例/金额 | F1: 发放周期 | G1: 发放条件 | H1: 计算公式 | I1: 备注
A2: 1 | B2: 月度销售提成 | C2: 电商运营助理 | D2: 个人负责销售额 | E2: 0.3%-0.8% | F2: 月度 | G2: 销售额达标且回款完成 | H2: 销售额*提成比例 | I2: 阶梯提成
A3: 2 | B3: 月度绩效奖金 | C3: 电商运营助理 | D3: 绩效标准金额 | E3: 0-120% | F3: 月度 | G3: 月度绩效得分≥60 | H3: 绩效标准*绩效系数 | I3: 与绩效考核表挂钩
A4: 3 | B4: 季度奖金 | C4: 电商运营助理 | D4: 月基本工资 | E4: 0.5-1.0个月 | F4: 季度 | G4: 季度目标达成 | H4: 基本工资*0.8 | I4: 每季度评估
A5: 4 | B5: 年度奖金 | C5: 电商运营助理 | D5: 月基本工资 | E5: 1.0-2.0个月 | F5: 年度 | G5: 年度绩效≥B且在职 | H5: 基本工资*1.5 | I5: 春节前发放
A6: 5 | B6: 项目奖金 | C6: 电商运营助理 | D6: 项目利润 | E6: 5%-15% | F6: 项目结束 | G6: 项目验收通过 | H6: 项目利润*分配比例 | I6: 专项激励
A7: 6 | B7: 全勤奖 | C7: 全员 | D7: 固定金额 | E7: 260元 | F7: 月度 | G7: 当月无缺勤迟到早退 | H7: 固定260元 | I7: 超3次取消
A8: 7 | B8: 伯乐奖 | C8: 全员 | D8: 固定金额 | E8: 500-2000元 | F8: 实时 | G8: 推荐人才成功转正 | H8: 按岗位级别定 | I8: 转正后发放
A9: 8 | B9: 年终分红 | C9: 核心员工 | D9: 公司年度利润 | E9: 0.5%-2% | F9: 年度 | G9: 入职满1年且绩效≥B | H9: 利润池*个人分配比例 | I9: 仅限资深员工

Sheet 福利明细
A1: 序号 | B1: 福利项目 | C1: 福利类型 | D1: 标准/金额 | E1: 享受条件 | F1: 发放方式 | G1: 备注
A2: 1 | B2: 养老保险 | C2: 法定福利 | D2: 基数*16%(单位)+8%(个人) | E2: 签订劳动合同 | F2: 社保代缴 | G2: 按当地社保政策
A3: 2 | B3: 医疗保险 | C3: 法定福利 | D3: 基数*8%(单位)+2%(个人) | E3: 签订劳动合同 | F3: 社保代缴 | G3: 含生育保险
A4: 3 | B4: 失业保险 | C4: 法定福利 | D4: 基数*0.5%(单位)+0.5%(个人) | E4: 签订劳动合同 | F4: 社保代缴 | G4: 按当地政策
A5: 4 | B5: 工伤保险 | C5: 法定福利 | D5: 基数*0.2%-1.4%(单位) | E5: 签订劳动合同 | F5: 社保代缴 | G5: 按行业风险等级
A6: 5 | B6: 住房公积金 | C6: 法定福利 | D6: 基数*5%-12%(双边) | E6: 签订劳动合同 | F6: 公积金代缴 | G6: 单位和个人同比例
A7: 6 | B7: 补充医疗保险 | C7: 补充福利 | D7: 约200元/人/年 | E7: 转正后 | F7: 商业保险 | G7: 覆盖门诊住院
A8: 7 | B8: 带薪年假 | C8: 法定福利 | D8: 5-15天/年 | E8: 入职满1年 | F8: 申请休假 | G8: 按工龄递增
A9: 8 | B9: 法定节假日 | C9: 法定福利 | D9: 11天/年 | E9: 全员 | F9: 带薪休假 | G9: 按国家规定
A10: 9 | B10: 节日福利 | C10: 补充福利 | D10: 300-500元/节 | E10: 全员 | F10: 实物/购物卡/现金 | G10: 春节/中秋/端午
A11: 10 | B11: 生日福利 | C11: 补充福利 | D11: 200元礼品/礼金 | E11: 全员 | F11: 生日当月发放 | G11: 或生日蛋糕券
A12: 11 | B12: 培训补贴 | C12: 补充福利 | D12: 1000-3000元/年 | E12: 年度培训计划内 | F12: 报销/直付 | G12: 外部课程/考证
A13: 12 | B13: 团建经费 | C13: 补充福利 | D13: 100-200元/人/月 | E13: 全员 | F13: 部门统筹 | G13: 季度或月度活动
... A18: 17 | B18: 通讯补贴 | C18: 津贴补贴 | D18: 130元/月 | E18: 运营/销售岗位 | F18: 随工资发放 | G18: 需报销话费发票

Sheet 计算示例
A1: 互联网/电商 · 电商运营助理 · 薪资计算示例
A3: 员工姓名 | B3: 张三 | C3: 部门 | D3: 互联网/电商事业部 | E3: 岗位 | F3: 电商运营助理
A4: 入职日期 | B4: 2026-03-01 | C4: 工龄 | D4: 1年 | E4: 职级 | F4: P2 专员
A5: 计薪月份 | B5: 2026-07 | C5: 应出勤天数 | D5: 21.75 | E5: 实际出勤天数 | F5: 21
A6: 基本工资 | B6: 4500 | C6: 岗位工资 | D6: 1800 | E6: 绩效工资标准 | F6: 2000
A7: 全勤奖标准 | B7: 260 | C7: 餐补标准 | D7: 390 | E7: 交通补贴标准 | F7: 260
A8: 通讯补贴标准 | B8: 130 | C8: 五险一金基数 | D8: 6500 | E8: 公积金比例 | F8: 0.05
A9: 城市 | B9: 广州 | C9: 城市系数 | D9: 1.3
A10: 薪资项目 | B10: 金额(元) | C10: 计算说明 | D10: 绩效考核示例
A11: 基本工资 | B11: 4500 | C11: 固定 | D11: 考核维度 | E11: 权重 | F11: 得分
A12: 岗位工资 | B12: 1800 | C12: 固定 | D12: 销售额达成率 | E12: 0.25 | F12: 85
A13: 绩效工资 | B13: =MAX(0.6,MIN(1.2,F20/100))*D8 | C13: 由加权绩效得分驱动 | D13: 订单处理效率 | E13: 0.15 | F13: 90
A14: 加班工资 | B14: 650 | C14: 实际加班/值班 | D14: 客户满意度 | E14: 0.15 | F14: 88
A15: 全勤奖 | B15: 260 | C15: 当月无缺勤 | D15: 库存准确率 | E15: 0.1 | F15: 95
A16: 餐补 | B16: 376.55 | C16: 标准/应出勤*实际出勤 | D16: 活动执行完成率 | E16: 0.1 | F16: 100
A17: 交通补贴 | B17: 260 | C17: 固定 | D17: 数据报表准确率 | E17: 0.1 | F17: 90
A18: 通讯补贴 | B18: 130 | C18: 固定 | D18: 工作态度与协作 | E18: 0.1 | F18: 92
A19: 应发工资 | B19: =SUM(B11:B18) | D19: 学习成长 | E19: 0.05 | F19: 85
A20: 五险一金(个人) | B20: =D8*(8%+2%+0.5%)+D8*F8 | C20: 养老+医疗+失业+公积金 | D20: 加权绩效得分 | E20: =SUMPRODUCT(E12:E19,F12:F19)
A21: 个税起征点 | B21: 5000
A22: 应纳税所得额 | B22: =MAX(B19-B20-B21,0)
A23: 个人所得税 | B23: =IF(B22<=0,0,IF(B22<=3000,B22*3%,IF(B22<=12000,B22*10%-210,IF(B22<=25000,B22*20%-1410,B22*25%-2660)))) | C23: 累计预扣法（简化）
A24: 实发工资 | B24: =B19-B20-B23
A26: 奖金计算示例
A27: 奖金项目 | B27: 金额(元) | C27: 计算说明
A28: 月度销售提成 | B28: 800 | C28: 按实际业绩计提
A29: 月度绩效奖金 | B29: =B13 | C29: 绩效工资联动
A30: 全勤奖 | B30: 260 | C30: 当月无缺勤
A31: 季度奖金(预估) | B31: 2250 | C31: 基本工资*系数
A32: 奖金合计 | B32: =SUM(B28:B31)
E33: 全年薪酬总包预估
E34: 项目 | F34: 金额(元/年)
E35: 年固定薪资 | F35: =B19*12
E36: 年浮动奖金(提成+绩效) | F36: =(B28+B29)*12
E37: 年终奖(1个月) | F37: =B11+B12
E38: 年福利(餐补+交通+通讯+节日) | F38: =(B16+B17+B18+B30)*12+1200
E39: 全年总现金收入 | F39: =F35+F36+F37+F38
A40: 合规状态 | B40: =COUNTIF(合规校验!F:F,"PASS")&"项通过/"&COUNTA(合规校验!F:F)-1&"项校验"

Sheet 合规校验
A1: 序号 | B1: 校验项 | C1: 规则 | D1: 当前值 | E1: 阈值 | F1: 结果 | G1: 说明
A2: 1 | B2: 最低工资合规 | C2: 基本工资 ≥ 2300元 | D2: 4500 | E2: 2300 | F2: =IF(D2>=E2,"PASS","BLOCK") | G2: 低于最低工资为严重违规
A3: 2 | B3: 社保基数下限 | C3: 社保基数 ≥ 5284元 | D3: 6500 | E3: 5284 | F3: =IF(D3>=E3,"PASS","WARN") | G3: 低于下限需按最低基数缴纳
A4: 3 | B4: 社保基数上限 | C4: 社保基数 ≤ 26421元 | D4: 6500 | E4: 26421 | F4: =IF(D4<=E4,"PASS","WARN") | G4: 超过上限按上限缴纳
A5: 4 | B5: 公积金比例合规 | C5: 比例在 5%-12% 之间 | D5: 0.05 | E5: 0.05 | F5: =IF(AND(D5>=E5,D5<=0.12),"PASS","WARN") | G5: 比例需符合当地政策
A6: 5 | B6: 绩效工资占比 | C6: 绩效工资 ≤ 固定薪酬*50% | D6: 2000 | E6: 3150 | F6: =IF(D6<=E6,"PASS","WARN") | G6: 占比过高影响收入稳定性
A7: 6 | B7: 个税合规 | C7: 应纳税所得额 ≥ 0 | D7: ='计算示例'!B22 | E7: 0 | F7: =IF(D7>=E7,"PASS","WARN") | G7: 应纳税所得额为负需检查
A8: 7 | B8: 实发工资为正 | C8: 实发工资 > 0 | D8: ='计算示例'!B24 | E8: 0 | F8: =IF(D8>0,"PASS","BLOCK") | G8: 实发工资必须为正

Sheet 绩效系数对照表
A1: 绩效得分区间 | B1: 绩效系数 | C1: 说明
A2: < 60 | B2: 0.6 | C2: 不合格，绩效奖金打折
A3: 60 - 70 | B3: 0.7 | C3: 待改进
A4: 70 - 80 | B4: 0.8 | C4: 合格
A5: 80 - 90 | B5: 0.9 | C5: 良好
A6: 90 - 100 | B6: 1.0 | C6: 达标
A7: 100 - 110 | B7: 1.1 | C7: 优秀
A8: >= 110 | B8: 1.2 | C8: 卓越
